cdm_reader_mapper/__init__.py
cdm_reader_mapper/properties.py
cdm_reader_mapper/cdm_mapper/__init__.py
cdm_reader_mapper/cdm_mapper/mapper.py
cdm_reader_mapper/cdm_mapper/properties.py
cdm_reader_mapper/cdm_mapper/reader.py
cdm_reader_mapper/cdm_mapper/writer.py
cdm_reader_mapper/cdm_mapper/codes/__init__.py
cdm_reader_mapper/cdm_mapper/codes/codes.py
cdm_reader_mapper/cdm_mapper/codes/common/__init__.py
cdm_reader_mapper/cdm_mapper/codes/common/location_quality.json
cdm_reader_mapper/cdm_mapper/codes/common/platform_sub_type.json
cdm_reader_mapper/cdm_mapper/codes/common/platform_type.json
cdm_reader_mapper/cdm_mapper/codes/common/primary_station_id_scheme.json
cdm_reader_mapper/cdm_mapper/codes/common/report_quality.json
cdm_reader_mapper/cdm_mapper/codes/common/ship_speed_knots.json
cdm_reader_mapper/cdm_mapper/codes/common/ship_speed_ms.json
cdm_reader_mapper/cdm_mapper/codes/common/station_course.json
cdm_reader_mapper/cdm_mapper/codes/common/wind_direction.json
cdm_reader_mapper/cdm_mapper/codes/craid/__init__.py
cdm_reader_mapper/cdm_mapper/codes/craid/location_accuracy.json
cdm_reader_mapper/cdm_mapper/codes/craid/location_method.json
cdm_reader_mapper/cdm_mapper/codes/craid/location_quality.json
cdm_reader_mapper/cdm_mapper/codes/craid/quality_flag.json
cdm_reader_mapper/cdm_mapper/codes/craid/time_quality.json
cdm_reader_mapper/cdm_mapper/codes/gdac/T_sign.json
cdm_reader_mapper/cdm_mapper/codes/gdac/WBT_sign.json
cdm_reader_mapper/cdm_mapper/codes/gdac/__init__.py
cdm_reader_mapper/cdm_mapper/codes/gdac/qc_flag.json
cdm_reader_mapper/cdm_mapper/codes/icoads/__init__.py
cdm_reader_mapper/cdm_mapper/codes/icoads/r300/__init__.py
cdm_reader_mapper/cdm_mapper/codes/icoads/r300/d701/__init__.py
cdm_reader_mapper/cdm_mapper/codes/icoads/r300/d701/at_units.json
cdm_reader_mapper/cdm_mapper/codes/icoads/r300/d701/baro_units.json
cdm_reader_mapper/cdm_mapper/codes/icoads/r300/d701/platform_sub_type.json
cdm_reader_mapper-2.1.1.dist-info/licenses/LICENSE
cdm_reader_mapper-2.1.1.dist-info/WHEEL
cdm_reader_mapper-2.1.1.dist-info/METADATA
cdm_reader_mapper-2.1.1.dist-info/RECORD
