Metadata-Version: 2.4
Name: cdm_reader_mapper
Version: 2.1.1
Summary: Common Data Model reader and mapper toolbox
Keywords: cdm_reader_mapper
Author-email: Ludwig Lierhammer <ludwig.lierhammer@dwd.de>, Joseph Siddons <joseph.siddons@noc.ac.uk>, Jan Marius Willruth <jan.willruth@dwd.de>, Axel Andersson <axel.andersson@dwd.de>, Tina Leiding <tina.leiding@dwd.de>, Richard Cornes <richard.cornes@noc.ac.uk>, Elizabeth Kent <eck@noc.ac.uk>
Maintainer-email: Ludwig Lierhammer <ludwig.lierhammer@dwd.de>, Joseph Siddons <joseph.siddons@noc.ac.uk>, Jan Marius Willruth <jan.willruth@dwd.de>
Requires-Python: >=3.10
Classifier: Development Status :: 5 - Production/Stable
Classifier: Intended Audience :: Developers
Classifier: Intended Audience :: Science/Research
Classifier: License :: OSI Approved :: Apache Software License
Classifier: Natural Language :: English
Classifier: Operating System :: OS Independent
Classifier: Programming Language :: Python :: 3
Classifier: Programming Language :: Python :: 3.10
Classifier: Programming Language :: Python :: 3.11
Classifier: Programming Language :: Python :: 3.12
Classifier: Programming Language :: Python :: 3.13
License-File: LICENSE
Requires-Dist: bottleneck >=1.3.1
Requires-Dist: dask[array] >=2024.8.1
Requires-Dist: datashader >=0.15.0
Requires-Dist: distributed >=2.0
Requires-Dist: h5netcdf >= 1.3.0
Requires-Dist: msgpack
Requires-Dist: netcdf4
Requires-Dist: numba >=0.60.0
Requires-Dist: pandas>=2.2.0
Requires-Dist: platformdirs >4.0.0
Requires-Dist: pyarrow >=15.0.0
Requires-Dist: python-slugify
Requires-Dist: recordlinkage >= 0.15
Requires-Dist: requests
Requires-Dist: swifter >=1.3.2
Requires-Dist: timezonefinder >6.5.0,<9.0.0
Requires-Dist: xarray >=2023.11.0,!=2024.10.0
Requires-Dist: cdm_reader_mapper[dev] ; extra == "all"
Requires-Dist: cdm_reader_mapper[docs] ; extra == "all"
Requires-Dist: black[jupyter] ==25.9.0 ; extra == "dev"
Requires-Dist: blackdoc ==0.4.4 ; extra == "dev"
Requires-Dist: codespell ==2.4.1 ; extra == "dev"
Requires-Dist: coverage >=7.5.0 ; extra == "dev"
Requires-Dist: coveralls >=4.0.1 ; extra == "dev"
Requires-Dist: deptry ==0.23.1 ; extra == "dev"
Requires-Dist: distributed >=2.0 ; extra == "dev"
Requires-Dist: flake8 >=7.1.1 ; extra == "dev"
Requires-Dist: flake8-rst-docstrings >=0.3.0 ; extra == "dev"
Requires-Dist: flit >=3.9.0 ; extra == "dev"
Requires-Dist: isort ==7.0.0 ; extra == "dev"
Requires-Dist: notebook ; extra == "dev"
Requires-Dist: pip >=24.2.0 ; extra == "dev"
Requires-Dist: pre-commit >=3.7 ; extra == "dev"
Requires-Dist: pylint >=3.3.1 ; extra == "dev"
Requires-Dist: pytest>=8.3.4 ; extra == "dev"
Requires-Dist: pytest-cov>=6.0.0 ; extra == "dev"
Requires-Dist: pytest-env>=1.1.5 ; extra == "dev"
Requires-Dist: ruff >=0.7.0 ; extra == "dev"
Requires-Dist: vulture ==2.14 ; extra == "dev"
Requires-Dist: ipykernel ; extra == "docs"
Requires-Dist: ipython >=8.5.0 ; extra == "docs"
Requires-Dist: myst-nb >=1.2.0 ; extra == "docs"
Requires-Dist: nbconvert >=7.16.4 ; extra == "docs"
Requires-Dist: numpydoc >=1.8.0 ; extra == "docs"
Requires-Dist: sphinx >=7.0.0 ; extra == "docs"
Requires-Dist: sphinx-autodoc-typehints ; extra == "docs"
Requires-Dist: sphinx-copybutton ; extra == "docs"
Requires-Dist: sphinx-book-theme >=1.0 ; extra == "docs"
Project-URL: Changelog, https://cdm_reader_mapper.readthedocs.io/en/latest/history.html
Project-URL: Homepage, https://cdm-reader-mapper.readthedocs.io
Project-URL: Issue tracker, https://github.com/glamod/cdm_reader_mapper
Project-URL: Source, https://github.com/glamod/cdm_reader_mapper
Provides-Extra: all
Provides-Extra: dev
Provides-Extra: docs
